[
  {
    "url": "https://www.youtube.com/watch?v=ESnXaMrb6CA",
    "title": "Plumage a la station service, en direction de le Norvège.",
    "text": "",
    "date_label": "Entrée 1",
    "thumb": "https://img.youtube.com/vi/ESnXaMrb6CA/hqdefault.jpg",
    "youtube_id": "ESnXaMrb6CA",
    "title_auto": "Plumage a la station service, en direction de le Norvège."
  },
  {
    "url": "https://www.youtube.com/watch?v=25OPjQqqfnk",
    "title": "Aalborg - Départ vers le Cap Nord à moto",
    "text": "",
    "date_label": "Entrée 2",
    "thumb": "https://img.youtube.com/vi/25OPjQqqfnk/hqdefault.jpg",
    "youtube_id": "25OPjQqqfnk",
    "title_auto": "Aalborg - Départ vers le Cap Nord à moto"
  },
  {
    "url": "https://www.youtube.com/watch?v=NoYJzdNpkqI",
    "title": "Phare de Lindesnes Norvège : Premier arrêt vers le Cap Nord à moto",
    "text": "",
    "date_label": "Entrée 3",
    "thumb": "https://img.youtube.com/vi/NoYJzdNpkqI/hqdefault.jpg",
    "youtube_id": "NoYJzdNpkqI",
    "title_auto": "Phare de Lindesnes Norvège : Premier arrêt vers le Cap Nord à moto"
  }
]