{
  "_meta": {
    "schema_version": "1.0",
    "page_type": "product",
    "slug": "intercoms",
    "last_updated": "2026-03-24",
    "updated_by": "batch"
  },
  "seo": {
    "title": "Test Intercom Moto : Sena vs Cardo, Quel Choisir ? | LCDMH",
    "description": "Tests intercoms moto Sena et Cardo en road trip : qualité audio, micro vent, Bluetooth, autonomie. Mon avis honnête pour bien choisir.",
    "keywords": "intercom moto, Sena moto, Cardo moto, test intercom moto, bluetooth casque moto, LCDMH",
    "canonical": "https://lcdmh.com/intercoms.html"
  },
  "hero": {
    "title": "Intercoms Moto",
    "slogan": "Sena & Cardo testés\nen conditions réelles",
    "features_line": "🎧 Audio HD • 📻 Radio FM • 📱 Bluetooth • 🗣️ Intercom • 🗺️ GPS compatible"
  },
  "intro": {
    "text": "J'ai testé plusieurs intercoms Sena et Cardo en conditions réelles sur mes road trips. Qualité audio, autonomie, résistance à la pluie — voici mes avis honnêtes."
  },
  "product": {
    "name": "Sena / Cardo Intercoms Moto",
    "tagline": "Les meilleurs intercoms moto testés en conditions réelles",
    "description": "Tests complets des intercoms Sena et Cardo : qualité audio, Bluetooth, compatibilité CarPlay et GPS moto.",
    "rating": 4.5,
    "rating_count": 0,
    "affiliate_url": "https://lcdmh.com/codes-promo.html",
    "note": "Codes promo Sena et Cardo disponibles sur la page codes promo"
  },
  "test_status": {
    "status": "done",
    "label": "TESTÉS — Road trips Europe",
    "text": "J'ai utilisé plusieurs intercoms Sena sur mes road trips. La qualité audio et la compatibilité avec les GPS CarPlay sont mes critères principaux.",
    "sub_text": "Les codes promo Sena et Cardo sont disponibles sur la page codes promo.",
    "rating": 4.5,
    "rating_label": "Avis après plusieurs road trips",
    "cta_label": "🎧 VOIR LES CODES PROMO INTERCOMS",
    "cta_url": "https://lcdmh.com/codes-promo.html"
  },
  "why_choose": [
    {
      "icon": "🎧",
      "title": "Audio HD",
      "text": "Qualité musicale et téléphonique excellente même à 130 km/h sur autoroute."
    },
    {
      "icon": "📱",
      "title": "Bluetooth multipoint",
      "text": "Connecté simultanément au téléphone, au GPS et à un autre intercom."
    },
    {
      "icon": "🗣️",
      "title": "Intercom motard",
      "text": "Communication en moto à moto jusqu'à 2 km selon les modèles."
    },
    {
      "icon": "💧",
      "title": "Résistant à la pluie",
      "text": "IPX5 minimum sur les modèles testés. Aucun problème sous la pluie."
    },
    {
      "icon": "🔋",
      "title": "Autonomie",
      "text": "Entre 10h et 20h selon les modèles. Suffisant pour une journée de route."
    },
    {
      "icon": "🗺️",
      "title": "Compatible GPS CarPlay",
      "text": "Les instructions de navigation s'intègrent directement dans l'audio de l'intercom."
    }
  ],
  "videos": {
    "enabled": true,
    "keywords": "intercom,sena,cardo",
    "max": 4
  },
  "partner": {
    "name": "Sena/Cardo",
    "contact": "",
    "commission": "",
    "awin": false,
    "platform": "direct"
  },
  "key_features": [
    {
      "icon": "🎧",
      "title": "Audio HD",
      "text": "Qualité musicale et téléphonique excellente même à 130 km/h sur autoroute.",
      "image": "https://images.unsplash.com/photo-1558618666-fcd25c85cd64?q=80&w=1974",
      "image_alt": "Intercom moto audio qualité"
    },
    {
      "icon": "🗣️",
      "title": "Intercom moto à moto",
      "text": "Communication en moto à moto jusqu'à 2 km selon les modèles. Indispensable en groupe.",
      "image": "https://images.unsplash.com/photo-1519003722824-194d4455a60c?q=80&w=1974",
      "image_alt": "Communication intercom groupe moto"
    },
    {
      "icon": "💧",
      "title": "Résistant à la pluie",
      "text": "IPX5 minimum sur les modèles testés. Aucun problème sous la pluie pendant des heures.",
      "image": "https://images.unsplash.com/photo-1558981359-219d6364c9c8?q=80&w=1974",
      "image_alt": "Intercom moto pluie étanche"
    }
  ]
}